tw_comments/__init__.py
tw_comments/cli.py
tw_comments/domains/author.py
tw_comments/domains/comment.py
tw_comments/domains/video.py
tw_comments/helpers/slack_helpers.py
tw_comments/services/comment_service.py
tw_comments/services/slack_service.py
tw_comments/services/video_service.py
tw_comments-0.1.3.dist-info/METADATA
tw_comments-0.1.3.dist-info/WHEEL
tw_comments-0.1.3.dist-info/entry_points.txt
tw_comments-0.1.3.dist-info/RECORD
