Metadata-Version: 2.1
Name: tw-comments
Version: 0.1.3
Summary: Bot to send new comments to channel in Slack
Author: Cleyson Lima
Author-email: cleysonph@gmail.com
Requires-Python: >=3.8,<4.0
Classifier: Programming Language :: Python :: 3
Classifier: Programming Language :: Python :: 3.8
Classifier: Programming Language :: Python :: 3.9
Classifier: Programming Language :: Python :: 3.10
Classifier: Programming Language :: Python :: 3.11
Requires-Dist: asyncclick (>=8.1.3.4,<9.0.0.0)
Requires-Dist: httpx (>=0.23.3,<0.24.0)
